memote/__init__.py
memote/_version.py
memote/jinja2_extension.py
memote/utils.py
memote/experimental/__init__.py
memote/experimental/config.py
memote/experimental/essentiality.py
memote/experimental/experiment.py
memote/experimental/experimental_base.py
memote/experimental/growth.py
memote/experimental/medium.py
memote/experimental/tabular.py
memote/experimental/schemata/__init__.py
memote/experimental/schemata/configuration.json
memote/suite/__init__.py
memote/suite/api.py
memote/suite/collect.py
memote/suite/cli/__init__.py
memote/suite/cli/callbacks.py
memote/suite/cli/config.py
memote/suite/cli/reports.py
memote/suite/cli/runner.py
memote/suite/reporting/__init__.py
memote/suite/reporting/config.py
memote/suite/reporting/diff.py
memote/suite/reporting/history.py
memote/suite/reporting/report.py
memote/suite/reporting/snapshot.py
memote/suite/results/__init__.py
memote/suite/results/history_manager.py
memote/suite/results/models.py
memote/suite/results/repo_result_manager.py
memote/suite/results/result.py
memote/suite/results/result_manager.py
memote/suite/results/sql_result_manager.py
memote/suite/templates/__init__.py
memote/suite/templates/index.html
memote/suite/templates/test_config.yml
memote/suite/templates/validation_template.html
memote/suite/tests/conftest.py
memote/suite/tests/test_annotation.py
memote/suite/tests/test_basic.py
memote/suite/tests/test_biomass.py
memote/suite/tests/test_consistency.py
memote/suite/tests/test_essentiality.py
memote/suite/tests/test_growth.py
memote/suite/tests/test_matrix.py
memote/suite/tests/test_sbml.py
memote/suite/tests/test_sbo.py
memote/suite/tests/test_thermodynamics.py
memote/support/__init__.py
memote/support/annotation.py
memote/support/basic.py
memote/support/biomass.py
memote/support/consistency.py
memote/support/consistency_helpers.py
memote/support/essentiality.py
memote/support/gpr_helpers.py
memote/support/helpers.py
memote/support/matrix.py
memote/support/sbo.py
memote/support/thermodynamics.py
memote-0.17.0.dist-info/AUTHORS.rst
memote-0.17.0.dist-info/LICENSE
memote-0.17.0.dist-info/METADATA
memote-0.17.0.dist-info/WHEEL
memote-0.17.0.dist-info/entry_points.txt
memote-0.17.0.dist-info/top_level.txt
memote-0.17.0.dist-info/RECORD
