Metadata-Version: 2.1
Name: memote
Version: 0.17.0
Summary: the genome-scale metabolic model test suite
Home-page: https://github.com/opencobra/memote
Download-URL: https://pypi.org/project/memote/
Author: Moritz E. Beber
Author-email: midnighter@posteo.net
License: Apache-2.0
Project-URL: Source Code, https://github.com/opencobra/memote
Project-URL: Documentation, https://memote.readthedocs.io
Project-URL: Bug Tracker, https://github.com/opencobra/memote/issues
Keywords: memote,metabolic model,constraint-based,COBRA,test suite,quality control,quality assurance
Classifier: Development Status :: 5 - Production/Stable
Classifier: Intended Audience :: Developers
Classifier: Intended Audience :: Science/Research
Classifier: License :: OSI Approved :: Apache Software License
Classifier: Natural Language :: English
Classifier: Operating System :: OS Independent
Classifier: Programming Language :: Python :: 3.8
Classifier: Programming Language :: Python :: 3.9
Classifier: Programming Language :: Python :: 3.10
Classifier: Programming Language :: Python :: 3.11
Classifier: Programming Language :: Python :: 3 :: Only
Classifier: Topic :: Scientific/Engineering :: Bio-Informatics
Requires-Python: >=3.6
License-File: LICENSE
License-File: AUTHORS.rst
Requires-Dist: click
Requires-Dist: click-configfile
Requires-Dist: click-log
Requires-Dist: importlib_resources>=1.3; python_version < "3.9"
Requires-Dist: six
Requires-Dist: future
Requires-Dist: pytest>=4.0
Requires-Dist: gitpython
Requires-Dist: PyGithub~=1.55
Requires-Dist: pandas
Requires-Dist: Jinja2
Requires-Dist: cookiecutter
Requires-Dist: cobra>=0.17
Requires-Dist: ruamel.yaml>=0.15
Requires-Dist: sympy
Requires-Dist: sqlalchemy
Requires-Dist: requests
Requires-Dist: numpydoc
Requires-Dist: pylru
Requires-Dist: pandera~=0.18
Requires-Dist: jsonschema~=4.20
Requires-Dist: depinfo~=2.2
Requires-Dist: requests
Provides-Extra: development
Requires-Dist: black; extra == "development"
Requires-Dist: isort; extra == "development"
Requires-Dist: tox; extra == "development"
